poly/__init__.py
poly/main.py
poly_cli-1.2.1.dist-info/METADATA
poly_cli-1.2.1.dist-info/WHEEL
poly_cli-1.2.1.dist-info/entry_points.txt
poly_cli-1.2.1.dist-info/licenses/LICENSE
poly_cli-1.2.1.dist-info/RECORD
