Metadata-Version: 2.4
Name: poly-cli
Version: 1.2.1
Summary: CLI tool for text and clipboard manipulation
Project-URL: Homepage, https://github.com/3digitdev/poly
Project-URL: Issues, https://github.com/3digitdev/poly/issues
Author-email: poly@3digit.dev
Maintainer-email: poly@3digit.dev
License-File: LICENSE
Classifier: License :: OSI Approved :: GNU General Public License v3 (GPLv3)
Classifier: Operating System :: MacOS
Classifier: Operating System :: Unix
Classifier: Programming Language :: Python :: 3
Requires-Python: >=3.12
Requires-Dist: click<9,>=8.1.0
Requires-Dist: pillow<11,>=10
Requires-Dist: pyjwt<3,>=2.8.0
Requires-Dist: pyperclip<2,>=1.9.0
Requires-Dist: pyyaml<7,>=6.0.2
Requires-Dist: rich<14,>=13.8.0
Requires-Dist: toml<1,>=0.10.2
Provides-Extra: dev
Requires-Dist: cython<4,>=3.0.10; extra == 'dev'
Requires-Dist: pip-tools<8,>=7.3.0; extra == 'dev'
Requires-Dist: pkginfo==1.12.1.2; extra == 'dev'
Requires-Dist: pre-commit<4,>=3.6.0; extra == 'dev'
Requires-Dist: pytest<9,>=8.0.2; extra == 'dev'
Requires-Dist: ruff<1,>=0.1.14; extra == 'dev'
Requires-Dist: twine==6.0.1; extra == 'dev'
